CHANGES.rst
LICENSE
MANIFEST.in
README.rst
setup.cfg
setup.py
ddd_api_gateway/__init__.py
ddd_api_gateway/__version__.py
ddd_api_gateway/api.py
ddd_api_gateway/api_repository.py
ddd_api_gateway/apigw.py
ddd_api_gateway/apigw_factory.py
ddd_api_gateway/apigw_validator.py
ddd_api_gateway/metadata.py
ddd_api_gateway/namespace.py
ddd_api_gateway/prototype.py
ddd_api_gateway/route_specification.py
ddd_api_gateway/upstream.py
ddd_api_gateway/upstream_repository.py
ddd_api_gateway.egg-info/PKG-INFO
ddd_api_gateway.egg-info/SOURCES.txt
ddd_api_gateway.egg-info/dependency_links.txt
ddd_api_gateway.egg-info/requires.txt
ddd_api_gateway.egg-info/top_level.txt
ddd_api_gateway/exception/__init__.py
ddd_api_gateway/exception/api_error.py
ddd_api_gateway/exception/api_gateway_base_exception.py
ddd_api_gateway/exception/metadata_error.py
ddd_api_gateway/exception/route_specification_error.py
ddd_api_gateway/exception/upstream_error.py
requirements/base.txt
requirements/ci.txt
requirements/test.txt
requirements/tox.txt