Metadata-Version: 1.1
Name: ddd-api-gateway
Version: 0.0.4
Summary: DDD base framework for python
Home-page: https://github.com/sunwei/ddd-api-gateway
Author: Sun Wei
Author-email: wayde.sun@gmail.com
License: UNKNOWN
Platform: UNKNOWN
Classifier: Development Status :: 4 - Beta
Classifier: Intended Audience :: Developers
Classifier: License :: OSI Approved :: MIT License
Classifier: Natural Language :: English
Classifier: Operating System :: OS Independent
Classifier: Programming Language :: Python
Classifier: Programming Language :: Python :: 3.4
Classifier: Programming Language :: Python :: 3.5
Classifier: Programming Language :: Python :: 3.6
Classifier: Topic :: Software Development :: Libraries :: Python Modules
